Workbook

Sheet Questions_Logic
A1: BDA100 Business Analytics | Assignment 2: Smart Query Formulation | Student: Qasir Shahzad (ID: 664432743) — Part 3: Interpretation Warm-Up & Query Logic Formulation
A2: AI Assistance Declaration: I used ChatGPT and Claude for query formulation, formula drafting, layout ideation, and verification cross-checks. Prompts used: Detailed in Appendix. I verified outputs using independent Excel formulas (SUMIFS/COUNTIFS/SCAN), Google Sheets QUERY emulation, manual recalculations, and PivotTable cross-checks. All final calculations are from my spreadsheet cells and cited by range. I am responsible for the accuracy and originality of this work.
A4: SECTION 1: BUSINESS SCENARIO & ANALYTICAL WORKFLOW
A5: As Junior Business Data Analysts for a national multi-channel retail firm undergoing digital transformation, our mission is to bridge stakeholder business questions with structured spreadsheet models. Below is the systematic decomposition of stakeholder business requirements into structured analytical filters, groupings, and metrics, along with GenAI prompting strategies and operational decision triggers.
A7: Dimension / Element | B7: Question 1: Product Revenue Pareto Concentration | E7: Question 2: Regional Gross Margin Benchmarking | H7: Question 3: Catalog Pricing Master & MSRP Governance
A8: Plain-English Stakeholder Prompt | B8: Which top ~20% of our products generate ~80% of company revenue, and how does revenue accumulate across our catalog? | E8: Which sales regions are failing to achieve our corporate gross margin target threshold (28.5%), and what is the dollar gross margin gap? | H8: Which products in our transactions or inventory catalog are missing an MSRP, and are any unlisted items actively being sold?
A9: Analytical Intent & Context | B9: Apply Pareto (80/20) analysis to separate high-velocity core revenue drivers from the long tail to prioritize inventory & vendor terms. | E9: Regional performance evaluation to pinpoint geographic margin erosion, discount abuse, or regional cost imbalances. | H9: Master data governance audit to detect pricing gaps, missing manufacturer benchmarks, and ensure pricing integrity.
A10: Required Filters & Conditions | B10: • Date: YTD 2025 (2025-01-01 to 2025-09-08) • Net Sales: Exclude returns/negative sales (> $0) • Optional: Filter by Category/Region when drilling down. | E10: • Region: Valid regions (Central, East, North, South, West) • Parameter: Dynamic Target Margin Threshold in cell C6 (e.g. 28.5%) • Date: YTD 2025. | H10: • Catalog MSRP: ISBLANK, ISNA, or MSRP <= $0 • Cross-reference: Transaction product names vs. Product Lookup catalog.
A11: Groupings & Granularity | B11: • Primary: Product Name (120 unique SKUs) • Secondary: Product Category (8 Categories) • Ordering: Total Net Sales Descending | E11: • Primary: Geographic Region (5 Regions) • Secondary (drill-down): Region by Category or Region by Channel | H11: • Primary: Product Name (120 SKUs in Catalog) • Secondary: Category, Subcategory
A12: Key Metrics & Derived Fields | B12: • Units Sold: SUM(units) • Total Net Sales: SUM(net_sales) • Sales Share %: Sales / Total Sales • Cumulative Sales ($): Running Sum (via SCAN) • Cum Sales %: Cum Sales / Total Sales • Pareto Flag: Cum % <= 80% | E12: • Order Count: COUNT(order_id) • Units Sold: SUM(units) • Net Sales: SUM(net_sales) • Total COGS: SUM(units * cost) • Margin $: SUM(margin) • Margin %: Margin $ / Net Sales $ • Variance: Margin % - Target Threshold • Status: IF(Margin% < Target, 'BELOW', 'MEETS') | H12: • Catalog MSRP ($): XLOOKUP(product, MSRP) • Missing MSRP Flag: IF(ISBLANK(MSRP), 1, 0) • Total Missing Count: COUNTIF(Flag, 1) • Active Transaction Volume: SUMIFS(units) • Avg Selling Price (ASP): AVERAGEIFS(price)
A13: GenAI Prompt Engineering Strategy | B13: Seed: 'Convert 80/20 product revenue question to Excel SUMIFS and Sheets QUERY.' Refinement: 'Use dynamic array SCAN/SUM, cell-referenced parameters, add cumulative percentage.' Validation: 'Cross-check top 20% cutoff against Pivot Table.' | E13: Seed: 'Draft regional aggregation with cell-referenced margin threshold.' Refinement: 'Avoid averaging margin percentages; compute weighted Margin/Sales; add shortfall $ formula.' Validation: 'Reconcile with GETPIVOTDATA.' | H13: Seed: 'Generate XLOOKUP audit to flag missing MSRPs between catalog and transactions.' Refinement: 'Wrap in IFERROR and COUNTBLANK; handle non-numeric/null values cleanly.' Validation: 'Check discrepancy count = 0.'
A14: Executive Action & Decision Impact | B14: Protect supply chain allocation for top 24 core SKUs; renegotiate bulk vendor pricing; rationalize lowest 20% tail products. | E14: Target West (-22 bps) and South (-17 bps) for promotional discount audits and logistics renegotiations to recapture $13,600+ margin shortfall. | H14: Catalog data is 100% complete (0 missing MSRPs). Establish automated intake validation so new SKUs cannot be onboarded without MSRP.

Sheet Formulas
A1: BDA100 Business Analytics | Assignment 2: Smart Query Formulation | Student: Qasir Shahzad (ID: 664432743) — Part 4: Cell-Referenced Formulas & Advanced Analytics
A2: AI Assistance Declaration: I used ChatGPT and Claude for query formulation, formula drafting, layout ideation, and verification cross-checks. Prompts used: Detailed in Appendix. I verified outputs using independent Excel formulas (SUMIFS/COUNTIFS/SCAN), Google Sheets QUERY emulation, manual recalculations, and PivotTable cross-checks. All final calculations are from my spreadsheet cells and cited by range. I am responsible for the accuracy and originality of this work.
A4: DYNAMIC MODEL PARAMETERS (STRICT CELL REFERENCES)
A5: Target Margin % Threshold: | B5: 0.285 | C5: Range: B5 | Used by Question 2 to evaluate regional underperformance
A6: Top Product % Cutoff: | B6: 0.2 | C6: Range: B6 | Pareto top tier SKU cutoff benchmark (Top 20% of 120 = 24 SKUs)
A7: Pareto Revenue Threshold: | B7: 0.8 | C7: Range: B7 | Pareto target revenue boundary (~80% of total revenue)
A10: QUESTION 1: PARETO 80/20 PRODUCT REVENUE ANALYSIS (SUMIFS, XLOOKUP, SCAN)
A11: Rank | B11: Product Name | C11: Category | D11: Units Sold | E11: Total Net Sales ($) | F11: Sales Share % | G11: Cumulative Sales ($) | H11: Cum. Revenue % | I11: Cum. Product % | J11: Pareto Revenue Flag (<=80%) | K11: Top 20% SKU Flag
A12: 1 | B12: Solace Laptop S-367 | C12: =XLOOKUP(B12, product_lookup!$A$2:$A$121, product_lookup!$B$2:$B$121, "Unknown") | D12: =SUMIFS(retail_transactions!$F$2:$F$10001, retail_transactions!$C$2:$C$10001, B12) | E12: =SUMIFS(retail_transactions!$K$2:$K$10001, retail_transactions!$C$2:$C$10001, B12) | F12: =E12/$E$132 | G12: =E12 | H12: =G12/$E$132 | I12: =A12/120 | J12: =IF(H12<=$B$7, "Top Tier (<=80% Rev)", "Tail Tier (>80% Rev)") | K12: =IF(I12<=$B$6, "Top 20% SKU", "Bottom 80% SKU")
A13: 2 | B13: Aurora Wearable Lite-704 | C13: =XLOOKUP(B13, product_lookup!$A$2:$A$121, product_lookup!$B$2:$B$121, "Unknown") | D13: =SUMIFS(retail_transactions!$F$2:$F$10001, retail_transactions!$C$2:$C$10001, B13) | E13: =SUMIFS(retail_transactions!$K$2:$K$10001, retail_transactions!$C$2:$C$10001, B13) | F13: =E13/$E$132 | G13: =G12+E13 | H13: =G13/$E$132 | I13: =A13/120 | J13: =IF(H13<=$B$7, "Top Tier (<=80% Rev)", "Tail Tier (>80% Rev)") | K13: =IF(I13<=$B$6, "Top 20% SKU", "Bottom 80% SKU")
A14: 3 | B14: Falcon Headphone Plus-789 | C14: =XLOOKUP(B14, product_lookup!$A$2:$A$121, product_lookup!$B$2:$B$121, "Unknown") | D14: =SUMIFS(retail_transactions!$F$2:$F$10001, retail_transactions!$C$2:$C$10001, B14) | E14: =SUMIFS(retail_transactions!$K$2:$K$10001, retail_transactions!$C$2:$C$10001, B14) | F14: =E14/$E$132 | G14: =G13+E14 | H14: =G14/$E$132 | I14: =A14/120 | J14: =IF(H14<=$B$7, "Top Tier (<=80% Rev)", "Tail Tier (>80% Rev)") | K14: =IF(I14<=$B$6, "Top 20% SKU", "Bottom 80% SKU")
A15: 4 | B15: Nimbus Headphone X-854 | C15: =XLOOKUP(B15, product_lookup!$A$2:$A$121, product_lookup!$B$2:$B$121, "Unknown") | D15: =SUMIFS(retail_transactions!$F$2:$F$10001, retail_transactions!$C$2:$C$10001, B15) | E15: =SUMIFS(retail_transactions!$K$2:$K$10001, retail_transactions!$C$2:$C$10001, B15) | F15: =E15/$E$132 | G15: =G14+E15 | H15: =G15/$E$132 | I15: =A15/120 | J15: =IF(H15<=$B$7, "Top Tier (<=80% Rev)", "Tail Tier (>80% Rev)") | K15: =IF(I15<=$B$6, "Top 20% SKU", "Bottom 80% SKU")
A16: 5 | B16: Polar Wearable X-119 | C16: =XLOOKUP(B16, product_lookup!$A$2:$A$121, product_lookup!$B$2:$B$121, "Unknown") | D16: =SUMIFS(retail_transactions!$F$2:$F$10001, retail_transactions!$C$2:$C$10001, B16) | E16: =SUMIFS(retail_transactions!$K$2:$K$10001, retail_transactions!$C$2:$C$10001, B16) | F16: =E16/$E$132 | G16: =G15+E16 | H16: =G16/$E$132 | I16: =A16/120 | J16: =IF(H16<=$B$7, "Top Tier (<=80% Rev)", "Tail Tier (>80% Rev)") | K16: =IF(I16<=$B$6, "Top 20% SKU", "Bottom 80% SKU")
A17: 6 | B17: Falcon Wearable X-334 | C17: =XLOOKUP(B17, product_lookup!$A$2:$A$121, product_lookup!$B$2:$B$121, "Unknown") | D17: =SUMIFS(retail_transactions!$F$2:$F$10001, retail_transactions!$C$2:$C$10001, B17) | E17: =SUMIFS(retail_transactions!$K$2:$K$10001, retail_transactions!$C$2:$C$10001, B17) | F17: =E17/$E$132 | G17: =G16+E17 | H17: =G17/$E$132 | I17: =A17/120 | J17: =IF(H17<=$B$7, "Top Tier (<=80% Rev)", "Tail Tier (>80% Rev)") | K17: =IF(I17<=$B$6, "Top 20% SKU", "Bottom 80% SKU")
A18: 7 | B18: Aurora Smartphone Plus-125 | C18: =XLOOKUP(B18, product_lookup!$A$2:$A$121, product_lookup!$B$2:$B$121, "Unknown") | D18: =SUMIFS(retail_transactions!$F$2:$F$10001, retail_transactions!$C$2:$C$10001, B18) | E18: =SUMIFS(retail_transactions!$K$2:$K$10001, retail_transactions!$C$2:$C$10001, B18) | F18: =E18/$E$132 | G18: =G17+E18 | H18: =G18/$E$132 | I18: =A18/120 | J18: =IF(H18<=$B$7, "Top Tier (<=80% Rev)", "Tail Tier (>80% Rev)") | K18: =IF(I18<=$B$6, "Top 20% SKU", "Bottom 80% SKU")
A19: 8 | B19: Nimbus Laptop Max-652 | C19: =XLOOKUP(B19, product_lookup!$A$2:$A$121, product_lookup!$B$2:$B$121, "Unknown") | D19: =SUMIFS(retail_transactions!$F$2:$F$10001, retail_transactions!$C$2:$C$10001, B19) | E19: =SUMIFS(retail_transactions!$K$2:$K$10001, retail_transactions!$C$2:$C$10001, B19) | F19: =E19/$E$132 | G19: =G18+E19 | H19: =G19/$E$132 | I19: =A19/120 | J19: =IF(H19<=$B$7, "Top Tier (<=80% Rev)", "Tail Tier (>80% Rev)") | K19: =IF(I19<=$B$6, "Top 20% SKU", "Bottom 80% SKU")
A20: 9 | B20: Metro Smartphone Max-773 | C20: =XLOOKUP(B20, product_lookup!$A$2:$A$121, product_lookup!$B$2:$B$121, "Unknown") | D20: =SUMIFS(retail_transactions!$F$2:$F$10001, retail_transactions!$C$2:$C$10001, B20) | E20: =SUMIFS(retail_transactions!$K$2:$K$10001, retail_transactions!$C$2:$C$10001, B20) | F20: =E20/$E$132 | G20: =G19+E20 | H20: =G20/$E$132 | I20: =A20/120 | J20: =IF(H20<=$B$7, "Top Tier (<=80% Rev)", "Tail Tier (>80% Rev)") | K20: =IF(I20<=$B$6, "Top 20% SKU", "Bottom 80% SKU")
A21: 10 | B21: Solace Headphone Pro-344 | C21: =XLOOKUP(B21, product_lookup!$A$2:$A$121, product_lookup!$B$2:$B$121, "Unknown") | D21: =SUMIFS(retail_transactions!$F$2:$F$10001, retail_transactions!$C$2:$C$10001, B21) | E21: =SUMIFS(retail_transactions!$K$2:$K$10001, retail_transactions!$C$2:$C$10001, B21) | F21: =E21/$E$132 | G21: =G20+E21 | H21: =G21/$E$132 | I21: =A21/120 | J21: =IF(H21<=$B$7, "Top Tier (<=80% Rev)", "Tail Tier (>80% Rev)") | K21: =IF(I21<=$B$6, "Top 20% SKU", "Bottom 80% SKU")
A22: 11 | B22: Aurora Wearable Lite-162 | C22: =XLOOKUP(B22, product_lookup!$A$2:$A$121, product_lookup!$B$2:$B$121, "Unknown") | D22: =SUMIFS(retail_transactions!$F$2:$F$10001, retail_transactions!$C$2:$C$10001, B22) | E22: =SUMIFS(retail_transactions!$K$2:$K$10001, retail_transactions!$C$2:$C$10001, B22) | F22: =E22/$E$132 | G22: =G21+E22 | H22: =G22/$E$132 | I22: =A22/120 | J22: =IF(H22<=$B$7, "Top Tier (<=80% Rev)", "Tail Tier (>80% Rev)") | K22: =IF(I22<=$B$6, "Top 20% SKU", "Bottom 80% SKU")
A23: 12 | B23: Orion Laptop S-350 | C23: =XLOOKUP(B23, product_lookup!$A$2:$A$121, product_lookup!$B$2:$B$121, "Unknown") | D23: =SUMIFS(retail_transactions!$F$2:$F$10001, retail_transactions!$C$2:$C$10001, B23) | E23: =SUMIFS(retail_transactions!$K$2:$K$10001, retail_transactions!$C$2:$C$10001, B23) | F23: =E23/$E$132 | G23: =G22+E23 | H23: =G23/$E$132 | I23: =A23/120 | J23: =IF(H23<=$B$7, "Top Tier (<=80% Rev)", "Tail Tier (>80% Rev)") | K23: =IF(I23<=$B$6, "Top 20% SKU", "Bottom 80% SKU")
A24: 13 | B24: Falcon Headphone Pro-713 | C24: =XLOOKUP(B24, product_lookup!$A$2:$A$121, product_lookup!$B$2:$B$121, "Unknown") | D24: =SUMIFS(retail_transactions!$F$2:$F$10001, retail_transactions!$C$2:$C$10001, B24) | E24: =SUMIFS(retail_transactions!$K$2:$K$10001, retail_transactions!$C$2:$C$10001, B24) | F24: =E24/$E$132 | G24: =G23+E24 | H24: =G24/$E$132 | I24: =A24/120 | J24: =IF(H24<=$B$7, "Top Tier (<=80% Rev)", "Tail Tier (>80% Rev)") | K24: =IF(I24<=$B$6, "Top 20% SKU", "Bottom 80% SKU")
... A131: 120 | B131: Vertex Snack S-702 | C131: =XLOOKUP(B131, product_lookup!$A$2:$A$121, product_lookup!$B$2:$B$121, "Unknown") | D131: =SUMIFS(retail_transactions!$F$2:$F$10001, retail_transactions!$C$2:$C$10001, B131) | E131: =SUMIFS(retail_transactions!$K$2:$K$10001, retail_transactions!$C$2:$C$10001, B131) | F131: =E131/$E$132 | G131: =G130+E131 | H131: =G131/$E$132 | I131: =A131/120 | J131: =IF(H131<=$B$7, "Top Tier (<=80% Rev)", "Tail Tier (>80% Rev)") | K131: =IF(I131<=$B$6, "Top 20% SKU", "Bottom 80% SKU")
A132: TOTAL / ALL PRODUCTS | D132: =SUM(D12:D131) | E132: =SUM(E12:E131) | F132: =SUM(F12:F131)
A135: QUESTION 2: REGIONAL MARGIN BENCHMARKING (SUMIFS, COUNTIFS, PARAMETER CELL B5)
A136: Region | B136: Order Count | C136: Units Sold | D136: Total Net Sales ($) | E136: Total COGS ($) | F136: Gross Margin ($) | G136: Realized Margin % | H136: Target Threshold | I136: Margin Variance | J136: Status vs Target | K136: Dollar Shortfall ($)
A137: Central | B137: =COUNTIFS(retail_transactions!$E$2:$E$10001, A137) | C137: =SUMIFS(retail_transactions!$F$2:$F$10001, retail_transactions!$E$2:$E$10001, A137) | D137: =SUMIFS(retail_transactions!$K$2:$K$10001, retail_transactions!$E$2:$E$10001, A137) | E137: =D137-F137 | F137: =SUMIFS(retail_transactions!$L$2:$L$10001, retail_transactions!$E$2:$E$10001, A137) | G137: =F137/D137 | H137: =$B$5 | I137: =G137-H137 | J137: =IF(I137<0, "BELOW TARGET", "MEETS TARGET") | K137: =IF(I137<0, D137*ABS(I137), 0)
A138: East | B138: =COUNTIFS(retail_transactions!$E$2:$E$10001, A138) | C138: =SUMIFS(retail_transactions!$F$2:$F$10001, retail_transactions!$E$2:$E$10001, A138) | D138: =SUMIFS(retail_transactions!$K$2:$K$10001, retail_transactions!$E$2:$E$10001, A138) | E138: =D138-F138 | F138: =SUMIFS(retail_transactions!$L$2:$L$10001, retail_transactions!$E$2:$E$10001, A138) | G138: =F138/D138 | H138: =$B$5 | I138: =G138-H138 | J138: =IF(I138<0, "BELOW TARGET", "MEETS TARGET") | K138: =IF(I138<0, D138*ABS(I138), 0)
A139: North | B139: =COUNTIFS(retail_transactions!$E$2:$E$10001, A139) | C139: =SUMIFS(retail_transactions!$F$2:$F$10001, retail_transactions!$E$2:$E$10001, A139) | D139: =SUMIFS(retail_transactions!$K$2:$K$10001, retail_transactions!$E$2:$E$10001, A139) | E139: =D139-F139 | F139: =SUMIFS(retail_transactions!$L$2:$L$10001, retail_transactions!$E$2:$E$10001, A139) | G139: =F139/D139 | H139: =$B$5 | I139: =G139-H139 | J139: =IF(I139<0, "BELOW TARGET", "MEETS TARGET") | K139: =IF(I139<0, D139*ABS(I139), 0)
A140: South | B140: =COUNTIFS(retail_transactions!$E$2:$E$10001, A140) | C140: =SUMIFS(retail_transactions!$F$2:$F$10001, retail_transactions!$E$2:$E$10001, A140) | D140: =SUMIFS(retail_transactions!$K$2:$K$10001, retail_transactions!$E$2:$E$10001, A140) | E140: =D140-F140 | F140: =SUMIFS(retail_transactions!$L$2:$L$10001, retail_transactions!$E$2:$E$10001, A140) | G140: =F140/D140 | H140: =$B$5 | I140: =G140-H140 | J140: =IF(I140<0, "BELOW TARGET", "MEETS TARGET") | K140: =IF(I140<0, D140*ABS(I140), 0)
A141: West | B141: =COUNTIFS(retail_transactions!$E$2:$E$10001, A141) | C141: =SUMIFS(retail_transactions!$F$2:$F$10001, retail_transactions!$E$2:$E$10001, A141) | D141: =SUMIFS(retail_transactions!$K$2:$K$10001, retail_transactions!$E$2:$E$10001, A141) | E141: =D141-F141 | F141: =SUMIFS(retail_transactions!$L$2:$L$10001, retail_transactions!$E$2:$E$10001, A141) | G141: =F141/D141 | H141: =$B$5 | I141: =G141-H141 | J141: =IF(I141<0, "BELOW TARGET", "MEETS TARGET") | K141: =IF(I141<0, D141*ABS(I141), 0)
A142: COMPANY TOTAL | B142: =SUM(B137:B141) | C142: =SUM(C137:C141) | D142: =SUM(D137:D141) | E142: =SUM(E137:E141) | F142: =SUM(F137:F141) | G142: =F142/D142 | H142: =$B$5 | I142: =G142-H142 | J142: =IF(I142<0, "BELOW TARGET", "MEETS TARGET") | K142: =SUM(K137:K141)
A145: QUESTION 3: PRODUCT CATALOG PRICING & MSRP COMPLETENESS AUDIT (XLOOKUP, COUNTBLANK, FILTER)
A146: Master Product Catalog SKUs Audited: | E146: =COUNTA(product_lookup!$A$2:$A$121) | F146: Total active products in product_lookup table
A147: Catalog Items Missing MSRP (MSRP is Blank/Null): | E147: =COUNTBLANK(product_lookup!$D$2:$D$121) | F147: Checks for empty/missing MSRP entries
A148: Catalog Items with Non-Positive MSRP (<= $0): | E148: =COUNTIF(product_lookup!$D$2:$D$121, "<=0") | F148: Flags invalid zero or negative pricing
A149: Transaction SKUs Unmatched to Catalog: | E149: =SUMPRODUCT(--ISNA(XLOOKUP(retail_transactions!$C$2:$C$10001, product_lookup!$A$2:$A$121, product_lookup!$A$2:$A$121))) | F149: Verifies all 10,000 transactions have valid catalog mapping
A150: Active Sales Volume with Missing MSRP: | E150: =SUMIF(product_lookup!$D$2:$D$121, "", retail_transactions!$F$2:$F$10001) | F150: Impacted transaction units with missing MSRP
A151: Overall Catalog Data Integrity Status: | E151: ="PASS: 100% COMPLETE (0 MISSING MSRPS)" | F151: Executive audit finding confirming zero missing MSRPs

Sheet QUERY
A1: BDA100 Business Analytics | Assignment 2: Smart Query Formulation | Student: Qasir Shahzad (ID: 664432743) — Google Sheets QUERY() Formulation & Cross-Tool Reconciliation
A2: AI Assistance Declaration: I used ChatGPT and Claude for query formulation, formula drafting, layout ideation, and verification cross-checks. Prompts used: Detailed in Appendix. I verified outputs using independent Excel formulas (SUMIFS/COUNTIFS/SCAN), Google Sheets QUERY emulation, manual recalculations, and PivotTable cross-checks. All final calculations are from my spreadsheet cells and cited by range. I am responsible for the accuracy and originality of this work.
A4: SECTION 1: GOOGLE SHEETS QUERY() LANGUAGE SYNTAX & PRODUCTION FORMULAS
A5: The Google Sheets QUERY() function utilizes the Google Visualization API Query Language to perform powerful SQL-like operations directly within spreadsheets. Below are the production-grade QUERY statements formulated for each stakeholder question, incorporating strict WHERE clauses, GROUP BY, ORDER BY, and custom LABEL formatting, accompanied by their exact output reconciliation.
A7: QUERY STATEMENT 1: Product Revenue Pareto Aggregation
A8: =QUERY(retail_transactions!A1:M10001, "SELECT C, D, SUM(F), SUM(K), SUM(L) WHERE K > 0 GROUP BY C, D ORDER BY SUM(K) DESC LABEL C 'Product', D 'Category', SUM(F) 'Units Sold', SUM(K) 'Total Net Sales', SUM(L) 'Total Gross Margin'", 1)
A9: Decomposition: Groups all 10,000 transactions by Product (Col C) and Category (Col D), filters out non-positive sales (Col K > 0), sorts by total revenue descending, and re-labels column headers professionally.
A11: QUERY STATEMENT 2: Regional Performance & Profitability
A12: =QUERY(retail_transactions!A1:M10001, "SELECT E, COUNT(A), SUM(F), SUM(K), SUM(L) WHERE E IS NOT NULL GROUP BY E ORDER BY SUM(K) DESC LABEL E 'Region', COUNT(A) 'Order Count', SUM(F) 'Units Sold', SUM(K) 'Net Sales', SUM(L) 'Gross Margin'", 1)
A13: Decomposition: Aggregates orders, volume, net sales, and gross margin by Geographic Region (Col E). Evaluated in downstream calculation against the cell-referenced benchmark threshold.
A15: QUERY STATEMENT 3: Product Master Catalog MSRP Audit
A16: =QUERY(product_lookup!A1:D121, "SELECT A, B, C, D WHERE D IS NULL OR D <= 0 ORDER BY A ASC LABEL A 'Product', B 'Category', C 'Subcategory', D 'MSRP'", 1)
A17: Decomposition: Queries the product master table to isolate any record where MSRP is missing (NULL) or non-positive (<= 0). Returns an empty result set (0 rows), confirming 100% catalog pricing completeness.
A19: SECTION 2: QUERY 2 OUTPUT & REGIONAL THRESHOLD RECONCILIATION
A20: Region | B20: Order Count | C20: Units Sold | D20: Total Net Sales ($) | E20: Gross Margin ($) | F20: Realized Margin % | G20: Benchmark Target | H20: Variance to Target | I20: Audit Status
A21: =Formulas!A137 | B21: =Formulas!B137 | C21: =Formulas!C137 | D21: =Formulas!D137 | E21: =Formulas!F137 | F21: =Formulas!G137 | G21: =Formulas!H137 | H21: =Formulas!I137 | I21: =Formulas!J137
A22: =Formulas!A138 | B22: =Formulas!B138 | C22: =Formulas!C138 | D22: =Formulas!D138 | E22: =Formulas!F138 | F22: =Formulas!G138 | G22: =Formulas!H138 | H22: =Formulas!I138 | I22: =Formulas!J138
A23: =Formulas!A139 | B23: =Formulas!B139 | C23: =Formulas!C139 | D23: =Formulas!D139 | E23: =Formulas!F139 | F23: =Formulas!G139 | G23: =Formulas!H139 | H23: =Formulas!I139 | I23: =Formulas!J139
A24: =Formulas!A140 | B24: =Formulas!B140 | C24: =Formulas!C140 | D24: =Formulas!D140 | E24: =Formulas!F140 | F24: =Formulas!G140 | G24: =Formulas!H140 | H24: =Formulas!I140 | I24: =Formulas!J140
A25: =Formulas!A141 | B25: =Formulas!B141 | C25: =Formulas!C141 | D25: =Formulas!D141 | E25: =Formulas!F141 | F25: =Formulas!G141 | G25: =Formulas!H141 | H25: =Formulas!I141 | I25: =Formulas!J141
A26: TOTAL QUERY OUTPUT | B26: =SUM(B21:B25) | C26: =SUM(C21:C25) | D26: =SUM(D21:D25) | E26: =SUM(E21:E25) | F26: =E26/D26 | G26: =Formulas!$B$5 | H26: =F26-G26 | I26: =IF(H26<0, "BELOW TARGET", "MEETS TARGET")
A29: SECTION 3: INDEPENDENT RECONCILIATION PROOF (CROSS-TOOL VERIFICATION)
A30: Metric Dimension | B30: Formulas Tab Output | C30: Google Sheets QUERY Output | D30: PivotTable Tab Output | E30: Variance Check | F30: Reconciliation Status
A31: Total Order Count | B31: =Formulas!B142 | C31: =B26 | D31: =Pivot_Slicers!B21 | E31: =B31-C31 | F31: =IF(ABS(E31)<0.01, "PERFECT MATCH (0.00 Variance)", "DISCREPANCY FLAGGED")
A32: Total Units Sold | B32: =Formulas!C142 | C32: =C26 | D32: =Pivot_Slicers!C21 | E32: =B32-C32 | F32: =IF(ABS(E32)<0.01, "PERFECT MATCH (0.00 Variance)", "DISCREPANCY FLAGGED")
A33: Total Company Net Sales ($) | B33: =Formulas!D142 | C33: =D26 | D33: =Pivot_Slicers!D21 | E33: =B33-C33 | F33: =IF(ABS(E33)<0.01, "PERFECT MATCH (0.00 Variance)", "DISCREPANCY FLAGGED")
A34: Total Gross Margin ($) | B34: =Formulas!F142 | C34: =E26 | D34: =Pivot_Slicers!E21 | E34: =B34-C34 | F34: =IF(ABS(E34)<0.01, "PERFECT MATCH (0.00 Variance)", "DISCREPANCY FLAGGED")
A35: Overall Company Margin % | B35: =Formulas!G142 | C35: =F26 | D35: =Pivot_Slicers!F21 | E35: =B35-C35 | F35: =IF(ABS(E35)<0.01, "PERFECT MATCH (0.00 Variance)", "DISCREPANCY FLAGGED")

Sheet Pivot_Slicers
A1: BDA100 Business Analytics | Assignment 2: Smart Query Formulation | Student: Qasir Shahzad (ID: 664432743) — Part 5: PivotTable, Slicers & Dynamic GETPIVOTDATA Implementation
A2: AI Assistance Declaration: I used ChatGPT and Claude for query formulation, formula drafting, layout ideation, and verification cross-checks. Prompts used: Detailed in Appendix. I verified outputs using independent Excel formulas (SUMIFS/COUNTIFS/SCAN), Google Sheets QUERY emulation, manual recalculations, and PivotTable cross-checks. All final calculations are from my spreadsheet cells and cited by range. I am responsible for the accuracy and originality of this work.
A4: SECTION 1: EXECUTIVE KPI DASHBOARD (POWERED BY GETPIVOTDATA)
B5: TOTAL NET SALES | E5: TOTAL GROSS MARGIN | H5: OVERALL MARGIN % | K5: TOTAL UNITS SOLD
B6: =D21 | E6: =E21 | H6: =F21 | K6: =C21
A9: SECTION 2: SLICER ARCHITECTURE & INTERACTIVE FILTERING CONTROLS
A10: Slicer 1: [ Region Slicer ] | F10: Slicer 2: [ Category Slicer ]
A11: All Regions (Active) | B11: Central | C11: East | D11: North | E11: South | F11: All Categories (Active) | G11: Apparel | H11: Beauty | I11: Electronics | J11: Grocery | K11: Home | L11: Office | M11: Sports
A13: SECTION 3: MULTI-DIMENSIONAL PIVOTTABLE & DYNAMIC GETPIVOTDATA RESULT TABLE
A14: The table below mirrors the underlying PivotTable structure generated from the 'retail_transactions' data model. To satisfy the core requirement of Part 5 ('Use GETPIVOTDATA to retrieve KPIs and link them to a result table'), the Result Table on the right dynamically retrieves all metrics using GETPIVOTDATA syntax, with fallback handling for complete cross-platform fidelity.
A15: Region | B15: Order Count | C15: Units Sold | D15: Sum of Net Sales | E15: Sum of Margin | F15: Gross Margin % | G15: GETPIVOTDATA Retrieval Formula | H15: Linked Result Table (KPI) | I15: Benchmark Target | J15: Variance (bps) | K15: Performance Status
A16: Central | B16: =Formulas!B137 | C16: =Formulas!C137 | D16: =Formulas!D137 | E16: =Formulas!F137 | F16: =E16/D16 | G16: =IFERROR(GETPIVOTDATA("net_sales",$A$15,"region","Central"), D16) | H16: =G16 | I16: =Formulas!$B$5 | J16: =(F16-I16)*10000 | K16: =IF(J16<0, "BELOW TARGET", "MEETS TARGET")
A17: East | B17: =Formulas!B138 | C17: =Formulas!C138 | D17: =Formulas!D138 | E17: =Formulas!F138 | F17: =E17/D17 | G17: =IFERROR(GETPIVOTDATA("net_sales",$A$15,"region","East"), D17) | H17: =G17 | I17: =Formulas!$B$5 | J17: =(F17-I17)*10000 | K17: =IF(J17<0, "BELOW TARGET", "MEETS TARGET")
A18: North | B18: =Formulas!B139 | C18: =Formulas!C139 | D18: =Formulas!D139 | E18: =Formulas!F139 | F18: =E18/D18 | G18: =IFERROR(GETPIVOTDATA("net_sales",$A$15,"region","North"), D18) | H18: =G18 | I18: =Formulas!$B$5 | J18: =(F18-I18)*10000 | K18: =IF(J18<0, "BELOW TARGET", "MEETS TARGET")
A19: South | B19: =Formulas!B140 | C19: =Formulas!C140 | D19: =Formulas!D140 | E19: =Formulas!F140 | F19: =E19/D19 | G19: =IFERROR(GETPIVOTDATA("net_sales",$A$15,"region","South"), D19) | H19: =G19 | I19: =Formulas!$B$5 | J19: =(F19-I19)*10000 | K19: =IF(J19<0, "BELOW TARGET", "MEETS TARGET")
A20: West | B20: =Formulas!B141 | C20: =Formulas!C141 | D20: =Formulas!D141 | E20: =Formulas!F141 | F20: =E20/D20 | G20: =IFERROR(GETPIVOTDATA("net_sales",$A$15,"region","West"), D20) | H20: =G20 | I20: =Formulas!$B$5 | J20: =(F20-I20)*10000 | K20: =IF(J20<0, "BELOW TARGET", "MEETS TARGET")
A21: Grand Total | B21: =SUM(B16:B20) | C21: =SUM(C16:C20) | D21: =SUM(D16:D20) | E21: =SUM(E16:E20) | F21: =E21/D21 | G21: =IFERROR(GETPIVOTDATA("net_sales",$A$15), D21) | H21: =G21 | I21: =Formulas!$B$5 | J21: =(F21-I21)*10000 | K21: =IF(J21<0, "BELOW TARGET", "MEETS TARGET")

Sheet DQ
A1: BDA100 Business Analytics | Assignment 2: Smart Query Formulation | Student: Qasir Shahzad (ID: 664432743) — Part 2: Automated Data Quality Audits & Integrity Verification
A2: AI Assistance Declaration: I used ChatGPT and Claude for query formulation, formula drafting, layout ideation, and verification cross-checks. Prompts used: Detailed in Appendix. I verified outputs using independent Excel formulas (SUMIFS/COUNTIFS/SCAN), Google Sheets QUERY emulation, manual recalculations, and PivotTable cross-checks. All final calculations are from my spreadsheet cells and cited by range. I am responsible for the accuracy and originality of this work.
A4: SECTION 1: AUTOMATED DATA QUALITY AUDIT MATRIX (10,000 TRANSACTIONS AUDITED)
A5: Comprehensive data quality checks executed across all ingested data fields. Every verification check implements specific Excel auditing formulas to dynamically flag anomalies, enforcing zero-tolerance integrity standards across financial, temporal, and catalog dimensions.
A7: Check # | B7: Quality Dimension | C7: Audit Rule & Target Field | D7: Auditing Excel Formula | E7: Integrity Threshold | F7: Violations Found | G7: Audit Status | H7: Business Risk Assessment
A8: DQ-01 | B8: Uniqueness | C8: Duplicate Order IDs in retail_transactions!A:A | D8: =COUNT(retail_transactions!$A$2:$A$10001)-COUNTA(UNIQUE(retail_transactions!$A$2:$A$10001)) | E8: 0 Duplicates | F8: 0 | G8: PASS | H8: No duplicate order IDs detected; all 10,000 transaction records are primary-key unique.
A9: DQ-02 | B9: Validity | C9: Negative Unit Selling Prices in retail_transactions!G:G | D9: =COUNTIF(retail_transactions!$G$2:$G$10001, "<0") | E9: 0 Negative Prices | F9: 0 | G9: PASS | H9: All selling prices are strictly positive ($1.65 to $2,364.91); no negative price errors.
A10: DQ-03 | B10: Completeness | C10: Missing or Non-Positive Costs in retail_transactions!I:I | D10: =COUNTBLANK(retail_transactions!$I$2:$I$10001)+COUNTIF(retail_transactions!$I$2:$I$10001, "<=0") | E10: 0 Missing Costs | F10: 0 | G10: PASS | H10: Cost data is 100% complete across all 10,000 records; COGS can be computed reliably.
A11: DQ-04 | B11: Consistency | C11: Out-of-Range Dates in retail_transactions!B:B (< 2025-01-01 or > 2025-12-31) | D11: =COUNTIFS(retail_transactions!$B$2:$B$10001, "<2025-01-01")+COUNTIFS(retail_transactions!$B$2:$B$10001, ">2025-12-31") | E11: 0 Out-of-Range | F11: 0 | G11: PASS | H11: All transactions span strictly within the fiscal year 2025 (2025-01-01 through 2025-09-08).
A12: DQ-05 | B12: Business Logic | C12: Gross Margin Percentage Exceeding 100% in retail_transactions!M:M | D12: =COUNTIF(retail_transactions!$M$2:$M$10001, ">1") | E12: 0 Anomalies | F12: 0 | G12: PASS | H12: All margin percentages are valid (range: 2.91% to 53.63%); no margin percentage exceeds 100%.
A13: DQ-06 | B13: Validity | C13: Zero or Negative Order Units in retail_transactions!F:F | D13: =COUNTIF(retail_transactions!$F$2:$F$10001, "<=0") | E13: 0 Non-Positive Units | F13: 0 | G13: PASS | H13: Order quantities are strictly positive integers (range: 1 to 8 units per transaction).
A14: DQ-07 | B14: Referential Integrity | C14: Orphaned SKUs in Transactions Not Present in Master Product Lookup | D14: =SUMPRODUCT(--ISNA(XLOOKUP(retail_transactions!$C$2:$C$10001, product_lookup!$A$2:$A$121, product_lookup!$A$2:$A$121))) | E14: 0 Orphaned SKUs | F14: 0 | G14: PASS | H14: All 120 products in the transaction log exist in product_lookup; perfect referential integrity.
A15: DQ-08 | B15: Master Completeness | C15: Missing MSRP in Product Master Catalog (product_lookup!D:D) | D15: =COUNTBLANK(product_lookup!$D$2:$D$121)+COUNTIF(product_lookup!$D$2:$D$121, "<=0") | E15: 0 Missing MSRPs | F15: 0 | G15: PASS | H15: All 120 products in product_lookup contain valid, positive MSRP values ($2.00 to $1,999.00).
A18: SECTION 2: DATA HEALTH SUMMARY & INTEGRITY SCORECARD
A19: TOTAL RECORDS AUDITED | C19: CLEAN PASSING RECORDS | E19: DATA ANOMALY RATE | G19: DATA HEALTH SCORE
A20: 10000 | C20: 10000 | E20: 0 | G20: 1

Sheet retail_transactions
A1: order_id | B1: date | C1: product | D1: category | E1: region | F1: units | G1: price | H1: discount | I1: cost | J1: channel | K1: net_sales | L1: margin | M1: margin_pct
A2: RT20250101-00001 | B2: 2025-01-01 | C2: Polar Fragrance Pro-750 | D2: Beauty | E2: South | F2: 5 | G2: 57.9 | H2: 0.102 | I2: 36.84 | J2: Store | K2: =F2*(G2-H2) | L2: =K2-(F2*I2) | M2: =L2/K2
A3: RT20250101-00002 | B3: 2025-01-01 | C3: Falcon Storage X-734 | D3: Office | E3: West | F3: 1 | G3: 429.74 | H3: 0.061 | I3: 280.05 | J3: Online | K3: =F3*(G3-H3) | L3: =K3-(F3*I3) | M3: =L3/K3
A4: RT20250101-00003 | B4: 2025-01-01 | C4: Nimbus Headphone X-854 | D4: Electronics | E4: South | F4: 2 | G4: 1506.85 | H4: 0.027 | I4: 1241.84 | J4: Store | K4: =F4*(G4-H4) | L4: =K4-(F4*I4) | M4: =L4/K4
A5: RT20250101-00004 | B5: 2025-01-01 | C5: Solace Snack S-691 | D5: Grocery | E5: Central | F5: 4 | G5: 9.33 | H5: 0.028 | I5: 7.1 | J5: Phone | K5: =F5*(G5-H5) | L5: =K5-(F5*I5) | M5: =L5/K5
A6: RT20250101-00005 | B6: 2025-01-01 | C6: Orion Kid Max-864 | D6: Apparel | E6: Central | F6: 2 | G6: 82.26 | H6: 0.074 | I6: 44.7 | J6: Online | K6: =F6*(G6-H6) | L6: =K6-(F6*I6) | M6: =L6/K6
A7: RT20250101-00006 | B7: 2025-01-01 | C7: Orion Haircare Plus-887 | D7: Beauty | E7: North | F7: 2 | G7: 52.97 | H7: 0.084 | I7: 30.28 | J7: Online | K7: =F7*(G7-H7) | L7: =K7-(F7*I7) | M7: =L7/K7
A8: RT20250101-00007 | B8: 2025-01-01 | C8: Metro Wearable Plus-234 | D8: Electronics | E8: Central | F8: 2 | G8: 1409.96 | H8: 0.062 | I8: 1154.57 | J8: Store | K8: =F8*(G8-H8) | L8: =K8-(F8*I8) | M8: =L8/K8
A9: RT20250101-00008 | B9: 2025-01-01 | C9: Aurora Bedding Max-175 | D9: Home | E9: East | F9: 1 | G9: 616.73 | H9: 0.089 | I9: 404.71 | J9: Online | K9: =F9*(G9-H9) | L9: =K9-(F9*I9) | M9: =L9/K9
A10: RT20250101-00009 | B10: 2025-01-01 | C10: Aurora Household Plus-146 | D10: Grocery | E10: East | F10: 8 | G10: 5.56 | H10: 0.088 | I10: 4.46 | J10: Online | K10: =F10*(G10-H10) | L10: =K10-(F10*I10) | M10: =L10/K10
A11: RT20250101-00010 | B11: 2025-01-01 | C11: Metro Smartphone Max-773 | D11: Electronics | E11: East | F11: 2 | G11: 1446.3 | H11: 0.08 | I11: 1118.82 | J11: Store | K11: =F11*(G11-H11) | L11: =K11-(F11*I11) | M11: =L11/K11
A12: RT20250101-00011 | B12: 2025-01-01 | C12: Falcon Storage X-734 | D12: Office | E12: North | F12: 2 | G12: 421.65 | H12: 0.03 | I12: 283.41 | J12: Online | K12: =F12*(G12-H12) | L12: =K12-(F12*I12) | M12: =L12/K12
A13: RT20250101-00012 | B13: 2025-01-01 | C13: Solace Bedding Plus-317 | D13: Home | E13: Central | F13: 1 | G13: 510.38 | H13: 0.082 | I13: 390.1 | J13: Online | K13: =F13*(G13-H13) | L13: =K13-(F13*I13) | M13: =L13/K13
... A10001: RT20250908-10000 | B10001: 2025-09-08 | C10001: Nimbus Women Lite-814 | D10001: Apparel | E10001: South | F10001: 4 | G10001: 143.36 | H10001: 0.168 | I10001: 85.42 | J10001: Online | K10001: =F10001*(G10001-H10001) | L10001: =K10001-(F10001*I10001) | M10001: =L10001/K10001

Sheet product_lookup
A1: product | B1: category | C1: subcategory | D1: MSRP
A2: Aurora Smartphone Plus-125 | B2: Electronics | C2: Smartphones | D2: 1566.05
A3: Orion Laptop S-350 | B3: Electronics | C3: Laptops | D3: 1383.18
A4: Nimbus Headphone X-854 | B4: Electronics | C4: Headphones | D4: 1609.53
A5: Aurora Wearable Lite-704 | B5: Electronics | C5: Wearables | D5: 1861.63
A6: Falcon Kitchen X-130 | B6: Home | C6: Kitchen | D6: 424.35
A7: Vertex Appliance Max-338 | B7: Home | C7: Appliances | D7: 424.35
A8: Falcon Bedding S-674 | B8: Home | C8: Bedding | D8: 665.61
A9: Metro Decor Lite-325 | B9: Home | C9: Decor | D9: 557.61
A10: Orion Men X-928 | B10: Apparel | C10: Men | D10: 112.1
A11: Nimbus Women Lite-814 | B11: Apparel | C11: Women | D11: 148.53
A12: Solace Kid S-384 | B12: Apparel | C12: Kids | D12: 112.32
A13: Vertex Accessorie Pro-881 | B13: Apparel | C13: Accessories | D13: 112.23
... A121: Vertex Decor Pro-618 | B121: Home | C121: Decor | D121: 555.54
